{
  "last_updated": "2026-03-18T18:45:57.652549+09:00",
  "data": [
    {
      "spend": 550205.0,
      "impressions": 23440,
      "clicks": 518,
      "reach": 0,
      "ctr": 2.21,
      "cpc": 0.0,
      "cpm": 23473.0,
      "purchases": 10,
      "purchase_value": 506819.0,
      "roas": 0.92,
      "cpa": 55020.0,
      "ad_id": "120243877242080020",
      "ad_name": "260313 KTX 조금덜소프트_27",
      "adset_name": "260313 KTX 전환",
      "campaign_name": "260303 일반 전환 캠페인"
    },
    {
      "spend": 63198.0,
      "impressions": 863,
      "clicks": 22,
      "reach": 0,
      "ctr": 2.55,
      "cpc": 0.0,
      "cpm": 73231.0,
      "purchases": 0,
      "purchase_value": 0.0,
      "roas": 0.0,
      "cpa": 0.0,
      "ad_id": "120243403696300020",
      "ad_name": "260303 장윤주 브랜디드 슈링크",
      "adset_name": "260303 브랜디드 슈링크",
      "campaign_name": "260303 일반 전환 캠페인"
    },
    {
      "spend": 59377.0,
      "impressions": 1164,
      "clicks": 24,
      "reach": 0,
      "ctr": 2.06,
      "cpc": 0.0,
      "cpm": 51011.0,
      "purchases": 1,
      "purchase_value": 59322.0,
      "roas": 1.0,
      "cpa": 59377.0,
      "ad_id": "120243967839280020",
      "ad_name": "260313_백지연_이뻐지는습관",
      "adset_name": "260315_백지연_1차",
      "campaign_name": "260303 일반 전환 캠페인"
    },
    {
      "spend": 30366.0,
      "impressions": 1974,
      "clicks": 17,
      "reach": 0,
      "ctr": 0.86,
      "cpc": 0.0,
      "cpm": 15383.0,
      "purchases": 0,
      "purchase_value": 0.0,
      "roas": 0.0,
      "cpa": 0.0,
      "ad_id": "120244001333230020",
      "ad_name": "KTX_소프트1_자막 - 사본",
      "adset_name": "260216_ASC_1차광고_세트",
      "campaign_name": "260216_ASC_1차광고"
    },
    {
      "spend": 27814.0,
      "impressions": 460,
      "clicks": 11,
      "reach": 0,
      "ctr": 2.39,
      "cpc": 0.0,
      "cpm": 60465.0,
      "purchases": 0,
      "purchase_value": 0.0,
      "roas": 0.0,
      "cpa": 0.0,
      "ad_id": "120242792148010020",
      "ad_name": "ASC_제미나이3",
      "adset_name": "260216_ASC_1차광고_세트",
      "campaign_name": "260216_ASC_1차광고"
    },
    {
      "spend": 20858.0,
      "impressions": 194,
      "clicks": 16,
      "reach": 0,
      "ctr": 8.25,
      "cpc": 0.0,
      "cpm": 107515.0,
      "purchases": 1,
      "purchase_value": 99200.0,
      "roas": 4.76,
      "cpa": 20858.0,
      "ad_id": "120242695764750020",
      "ad_name": "ASC_1차_궁금증1_영상",
      "adset_name": "260216_ASC_1차광고_세트",
      "campaign_name": "260216_ASC_1차광고"
    },
    {
      "spend": 19334.0,
      "impressions": 440,
      "clicks": 11,
      "reach": 0,
      "ctr": 2.5,
      "cpc": 0.0,
      "cpm": 43941.0,
      "purchases": 0,
      "purchase_value": 0.0,
      "roas": 0.0,
      "cpa": 0.0,
      "ad_id": "120243954678250020",
      "ad_name": "260313 KTX 소프트 ASMR_27",
      "adset_name": "260315 KTX - 메신저 전환",
      "campaign_name": "전환 메신저 [전환수 목표]"
    },
    {
      "spend": 19107.0,
      "impressions": 768,
      "clicks": 11,
      "reach": 0,
      "ctr": 1.43,
      "cpc": 0.0,
      "cpm": 24879.0,
      "purchases": 1,
      "purchase_value": 33133.0,
      "roas": 1.73,
      "cpa": 19107.0,
      "ad_id": "120243954846910020",
      "ad_name": "260315 KTX 조금덜소프트 카카오_27 - 사본",
      "adset_name": "260315 KTX 댓글유도",
      "campaign_name": "260303 일반 전환 캠페인"
    },
    {
      "spend": 16661.0,
      "impressions": 268,
      "clicks": 8,
      "reach": 0,
      "ctr": 2.99,
      "cpc": 0.0,
      "cpm": 62168.0,
      "purchases": 0,
      "purchase_value": 0.0,
      "roas": 0.0,
      "cpa": 0.0,
      "ad_id": "120244002589210020",
      "ad_name": "ASC_1차_슈링크1_영상 - 사본",
      "adset_name": "260316_슈링크",
      "campaign_name": "260303 일반 전환 캠페인"
    },
    {
      "spend": 14869.0,
      "impressions": 148,
      "clicks": 4,
      "reach": 0,
      "ctr": 2.7,
      "cpc": 0.0,
      "cpm": 100466.0,
      "purchases": 1,
      "purchase_value": 95827.0,
      "roas": 6.44,
      "cpa": 14869.0,
      "ad_id": "120244002854830020",
      "ad_name": "260227_에디티 - 사본",
      "adset_name": "260316_제로+에디티",
      "campaign_name": "260303 일반 전환 캠페인"
    },
    {
      "spend": 14157.0,
      "impressions": 162,
      "clicks": 5,
      "reach": 0,
      "ctr": 3.09,
      "cpc": 0.0,
      "cpm": 87389.0,
      "purchases": 0,
      "purchase_value": 0.0,
      "roas": 0.0,
      "cpa": 0.0,
      "ad_id": "120244002342130020",
      "ad_name": "ASC_1차_궁금증1_영상 - 사본",
      "adset_name": "260316_궁금증",
      "campaign_name": "260303 일반 전환 캠페인"
    },
    {
      "spend": 13425.0,
      "impressions": 403,
      "clicks": 34,
      "reach": 0,
      "ctr": 8.44,
      "cpc": 0.0,
      "cpm": 33313.0,
      "purchases": 0,
      "purchase_value": 0.0,
      "roas": 0.0,
      "cpa": 0.0,
      "ad_id": "120242715820950020",
      "ad_name": "260217 제로제로 회춘_비밀",
      "adset_name": "260217 제로제로 회춘-메신져",
      "campaign_name": "전환 메신저 [대화수 목표]"
    },
    {
      "spend": 11011.0,
      "impressions": 142,
      "clicks": 5,
      "reach": 0,
      "ctr": 3.52,
      "cpc": 0.0,
      "cpm": 77542.0,
      "purchases": 0,
      "purchase_value": 0.0,
      "roas": 0.0,
      "cpa": 0.0,
      "ad_id": "120244002854850020",
      "ad_name": "ASC_제로제로 - 사본",
      "adset_name": "260316_제로+에디티",
      "campaign_name": "260303 일반 전환 캠페인"
    },
    {
      "spend": 8981.0,
      "impressions": 243,
      "clicks": 26,
      "reach": 0,
      "ctr": 10.7,
      "cpc": 0.0,
      "cpm": 36959.0,
      "purchases": 0,
      "purchase_value": 0.0,
      "roas": 0.0,
      "cpa": 0.0,
      "ad_id": "120243954941020020",
      "ad_name": "260315 KTX1메신저",
      "adset_name": "260315 KTX 메신저",
      "campaign_name": "전환 메신저 [대화수 목표]"
    },
    {
      "spend": 6872.0,
      "impressions": 113,
      "clicks": 7,
      "reach": 0,
      "ctr": 6.19,
      "cpc": 0.0,
      "cpm": 60814.0,
      "purchases": 0,
      "purchase_value": 0.0,
      "roas": 0.0,
      "cpa": 0.0,
      "ad_id": "120242695290790020",
      "ad_name": "ASC_1차_고밀도_단컷",
      "adset_name": "260216_ASC_1차광고_세트",
      "campaign_name": "260216_ASC_1차광고"
    },
    {
      "spend": 5933.0,
      "impressions": 79,
      "clicks": 3,
      "reach": 0,
      "ctr": 3.8,
      "cpc": 0.0,
      "cpm": 75101.0,
      "purchases": 0,
      "purchase_value": 0.0,
      "roas": 0.0,
      "cpa": 0.0,
      "ad_id": "120244002445030020",
      "ad_name": "궁금증1-1_수정 - 사본",
      "adset_name": "260316_궁금증",
      "campaign_name": "260303 일반 전환 캠페인"
    },
    {
      "spend": 3136.0,
      "impressions": 79,
      "clicks": 11,
      "reach": 0,
      "ctr": 13.92,
      "cpc": 0.0,
      "cpm": 39696.0,
      "purchases": 0,
      "purchase_value": 0.0,
      "roas": 0.0,
      "cpa": 0.0,
      "ad_id": "120243954962380020",
      "ad_name": "260315 KTX2메신저",
      "adset_name": "260315 KTX 메신저",
      "campaign_name": "전환 메신저 [대화수 목표]"
    },
    {
      "spend": 3108.0,
      "impressions": 74,
      "clicks": 5,
      "reach": 0,
      "ctr": 6.76,
      "cpc": 0.0,
      "cpm": 42000.0,
      "purchases": 0,
      "purchase_value": 0.0,
      "roas": 0.0,
      "cpa": 0.0,
      "ad_id": "120244001333220020",
      "ad_name": "260307_서정민_독백_롱 - 사본",
      "adset_name": "260216_ASC_1차광고_세트",
      "campaign_name": "260216_ASC_1차광고"
    },
    {
      "spend": 2761.0,
      "impressions": 56,
      "clicks": 0,
      "reach": 0,
      "ctr": 0.0,
      "cpc": 0.0,
      "cpm": 49304.0,
      "purchases": 0,
      "purchase_value": 0.0,
      "roas": 0.0,
      "cpa": 0.0,
      "ad_id": "120244002589220020",
      "ad_name": "ASC_1차_슈링크2_영상 - 사본",
      "adset_name": "260316_슈링크",
      "campaign_name": "260303 일반 전환 캠페인"
    },
    {
      "spend": 1993.0,
      "impressions": 41,
      "clicks": 2,
      "reach": 0,
      "ctr": 4.88,
      "cpc": 0.0,
      "cpm": 48610.0,
      "purchases": 0,
      "purchase_value": 0.0,
      "roas": 0.0,
      "cpa": 0.0,
      "ad_id": "120243967995390020",
      "ad_name": "260313_백지연_KTX결혼",
      "adset_name": "260315_백지연_1차",
      "campaign_name": "260303 일반 전환 캠페인"
    }
  ],
  "yesterday_data": [
    {
      "spend": 454212.0,
      "impressions": 21941,
      "clicks": 452,
      "reach": 0,
      "ctr": 2.06,
      "cpc": 0.0,
      "cpm": 20702.0,
      "purchases": 8,
      "purchase_value": 573895.0,
      "roas": 1.26,
      "cpa": 56776.0,
      "ad_id": "120243877242080020",
      "ad_name": "260313 KTX 조금덜소프트_27",
      "adset_name": "260313 KTX 전환",
      "campaign_name": "260303 일반 전환 캠페인"
    },
    {
      "spend": 413136.0,
      "impressions": 21324,
      "clicks": 488,
      "reach": 0,
      "ctr": 2.29,
      "cpc": 0.0,
      "cpm": 19374.0,
      "purchases": 3,
      "purchase_value": 132333.0,
      "roas": 0.32,
      "cpa": 137712.0,
      "ad_id": "120243876587730020",
      "ad_name": "260313 KTX 조금덜소프트 카카오_27 - 사본",
      "adset_name": "260313 KTX 전환",
      "campaign_name": "260303 일반 전환 캠페인"
    },
    {
      "spend": 95427.0,
      "impressions": 1611,
      "clicks": 78,
      "reach": 0,
      "ctr": 4.84,
      "cpc": 0.0,
      "cpm": 59235.0,
      "purchases": 1,
      "purchase_value": 60300.0,
      "roas": 0.63,
      "cpa": 95427.0,
      "ad_id": "120243954678250020",
      "ad_name": "260313 KTX 소프트 ASMR_27",
      "adset_name": "260315 KTX - 메신저 전환",
      "campaign_name": "전환 메신저 [전환수 목표]"
    },
    {
      "spend": 69219.0,
      "impressions": 922,
      "clicks": 20,
      "reach": 0,
      "ctr": 2.17,
      "cpc": 0.0,
      "cpm": 75075.0,
      "purchases": 0,
      "purchase_value": 0.0,
      "roas": 0.0,
      "cpa": 0.0,
      "ad_id": "120243403696300020",
      "ad_name": "260303 장윤주 브랜디드 슈링크",
      "adset_name": "260303 브랜디드 슈링크",
      "campaign_name": "260303 일반 전환 캠페인"
    },
    {
      "spend": 67938.0,
      "impressions": 3843,
      "clicks": 40,
      "reach": 0,
      "ctr": 1.04,
      "cpc": 0.0,
      "cpm": 17678.0,
      "purchases": 1,
      "purchase_value": 114600.0,
      "roas": 1.69,
      "cpa": 67938.0,
      "ad_id": "120244001333230020",
      "ad_name": "KTX_소프트1_자막 - 사본",
      "adset_name": "260216_ASC_1차광고_세트",
      "campaign_name": "260216_ASC_1차광고"
    },
    {
      "spend": 55203.0,
      "impressions": 982,
      "clicks": 20,
      "reach": 0,
      "ctr": 2.04,
      "cpc": 0.0,
      "cpm": 56215.0,
      "purchases": 1,
      "purchase_value": 62794.0,
      "roas": 1.14,
      "cpa": 55203.0,
      "ad_id": "120243967839280020",
      "ad_name": "260313_백지연_이뻐지는습관",
      "adset_name": "260315_백지연_1차",
      "campaign_name": "260303 일반 전환 캠페인"
    },
    {
      "spend": 42945.0,
      "impressions": 664,
      "clicks": 6,
      "reach": 0,
      "ctr": 0.9,
      "cpc": 0.0,
      "cpm": 64676.0,
      "purchases": 0,
      "purchase_value": 0.0,
      "roas": 0.0,
      "cpa": 0.0,
      "ad_id": "120244015286130020",
      "ad_name": "260316 KTX_에디티1",
      "adset_name": "260316 KTX_에디티1",
      "campaign_name": "260303 일반 전환 캠페인"
    },
    {
      "spend": 42944.0,
      "impressions": 1485,
      "clicks": 32,
      "reach": 0,
      "ctr": 2.15,
      "cpc": 0.0,
      "cpm": 28919.0,
      "purchases": 0,
      "purchase_value": 0.0,
      "roas": 0.0,
      "cpa": 0.0,
      "ad_id": "120243954846900020",
      "ad_name": "260315 KTX 조금덜소프트_27",
      "adset_name": "260315 KTX 댓글유도",
      "campaign_name": "260303 일반 전환 캠페인"
    },
    {
      "spend": 31824.0,
      "impressions": 436,
      "clicks": 14,
      "reach": 0,
      "ctr": 3.21,
      "cpc": 0.0,
      "cpm": 72991.0,
      "purchases": 1,
      "purchase_value": 37100.0,
      "roas": 1.17,
      "cpa": 31824.0,
      "ad_id": "120242792148010020",
      "ad_name": "ASC_제미나이3",
      "adset_name": "260216_ASC_1차광고_세트",
      "campaign_name": "260216_ASC_1차광고"
    },
    {
      "spend": 22121.0,
      "impressions": 251,
      "clicks": 11,
      "reach": 0,
      "ctr": 4.38,
      "cpc": 0.0,
      "cpm": 88131.0,
      "purchases": 1,
      "purchase_value": 36900.0,
      "roas": 1.67,
      "cpa": 22121.0,
      "ad_id": "120242695764750020",
      "ad_name": "ASC_1차_궁금증1_영상",
      "adset_name": "260216_ASC_1차광고_세트",
      "campaign_name": "260216_ASC_1차광고"
    },
    {
      "spend": 22043.0,
      "impressions": 252,
      "clicks": 13,
      "reach": 0,
      "ctr": 5.16,
      "cpc": 0.0,
      "cpm": 87472.0,
      "purchases": 1,
      "purchase_value": 121421.0,
      "roas": 5.51,
      "cpa": 22043.0,
      "ad_id": "120244002342130020",
      "ad_name": "ASC_1차_궁금증1_영상 - 사본",
      "adset_name": "260316_궁금증",
      "campaign_name": "260303 일반 전환 캠페인"
    },
    {
      "spend": 20665.0,
      "impressions": 327,
      "clicks": 9,
      "reach": 0,
      "ctr": 2.75,
      "cpc": 0.0,
      "cpm": 63196.0,
      "purchases": 0,
      "purchase_value": 0.0,
      "roas": 0.0,
      "cpa": 0.0,
      "ad_id": "120244002589210020",
      "ad_name": "ASC_1차_슈링크1_영상 - 사본",
      "adset_name": "260316_슈링크",
      "campaign_name": "260303 일반 전환 캠페인"
    },
    {
      "spend": 19490.0,
      "impressions": 198,
      "clicks": 7,
      "reach": 0,
      "ctr": 3.54,
      "cpc": 0.0,
      "cpm": 98434.0,
      "purchases": 2,
      "purchase_value": 107235.0,
      "roas": 5.5,
      "cpa": 9745.0,
      "ad_id": "120244002854850020",
      "ad_name": "ASC_제로제로 - 사본",
      "adset_name": "260316_제로+에디티",
      "campaign_name": "260303 일반 전환 캠페인"
    },
    {
      "spend": 19012.0,
      "impressions": 414,
      "clicks": 7,
      "reach": 0,
      "ctr": 1.69,
      "cpc": 0.0,
      "cpm": 45923.0,
      "purchases": 0,
      "purchase_value": 0.0,
      "roas": 0.0,
      "cpa": 0.0,
      "ad_id": "120244002786070020",
      "ad_name": "ASC_제미나이3 - 사본",
      "adset_name": "260316_제미나이",
      "campaign_name": "260303 일반 전환 캠페인"
    },
    {
      "spend": 17021.0,
      "impressions": 746,
      "clicks": 17,
      "reach": 0,
      "ctr": 2.28,
      "cpc": 0.0,
      "cpm": 22816.0,
      "purchases": 1,
      "purchase_value": 36605.0,
      "roas": 2.15,
      "cpa": 17021.0,
      "ad_id": "120243954846910020",
      "ad_name": "260315 KTX 조금덜소프트 카카오_27 - 사본",
      "adset_name": "260315 KTX 댓글유도",
      "campaign_name": "260303 일반 전환 캠페인"
    },
    {
      "spend": 10896.0,
      "impressions": 269,
      "clicks": 17,
      "reach": 0,
      "ctr": 6.32,
      "cpc": 0.0,
      "cpm": 40506.0,
      "purchases": 0,
      "purchase_value": 0.0,
      "roas": 0.0,
      "cpa": 0.0,
      "ad_id": "120243954941020020",
      "ad_name": "260315 KTX1메신저",
      "adset_name": "260315 KTX 메신저",
      "campaign_name": "전환 메신저 [대화수 목표]"
    },
    {
      "spend": 10546.0,
      "impressions": 307,
      "clicks": 17,
      "reach": 0,
      "ctr": 5.54,
      "cpc": 0.0,
      "cpm": 34352.0,
      "purchases": 0,
      "purchase_value": 0.0,
      "roas": 0.0,
      "cpa": 0.0,
      "ad_id": "120243954962380020",
      "ad_name": "260315 KTX2메신저",
      "adset_name": "260315 KTX 메신저",
      "campaign_name": "전환 메신저 [대화수 목표]"
    },
    {
      "spend": 10317.0,
      "impressions": 209,
      "clicks": 2,
      "reach": 0,
      "ctr": 0.96,
      "cpc": 0.0,
      "cpm": 49364.0,
      "purchases": 0,
      "purchase_value": 0.0,
      "roas": 0.0,
      "cpa": 0.0,
      "ad_id": "120243967995390020",
      "ad_name": "260313_백지연_KTX결혼",
      "adset_name": "260315_백지연_1차",
      "campaign_name": "260303 일반 전환 캠페인"
    },
    {
      "spend": 9187.0,
      "impressions": 239,
      "clicks": 19,
      "reach": 0,
      "ctr": 7.95,
      "cpc": 0.0,
      "cpm": 38439.0,
      "purchases": 0,
      "purchase_value": 0.0,
      "roas": 0.0,
      "cpa": 0.0,
      "ad_id": "120242715820950020",
      "ad_name": "260217 제로제로 회춘_비밀",
      "adset_name": "260217 제로제로 회춘-메신져",
      "campaign_name": "전환 메신저 [대화수 목표]"
    },
    {
      "spend": 8385.0,
      "impressions": 111,
      "clicks": 2,
      "reach": 0,
      "ctr": 1.8,
      "cpc": 0.0,
      "cpm": 75541.0,
      "purchases": 0,
      "purchase_value": 0.0,
      "roas": 0.0,
      "cpa": 0.0,
      "ad_id": "120244002681480020",
      "ad_name": "예뻐지려면1 - 사본",
      "adset_name": "260316_예뻐지려면",
      "campaign_name": "260303 일반 전환 캠페인"
    }
  ]
}