{
  "last_updated": "2026-03-16T23:19:36.877033+09:00",
  "data": [
    {
      "spend": 778096.0,
      "impressions": 55933,
      "clicks": 938,
      "reach": 0,
      "ctr": 1.68,
      "cpc": 0.0,
      "cpm": 13911.0,
      "purchases": 12,
      "purchase_value": 628432.0,
      "roas": 0.81,
      "cpa": 64841.0,
      "ad_id": "120243876587730020",
      "ad_name": "260313 KTX 조금덜소프트 카카오_27 - 사본",
      "adset_name": "260313 KTX 전환",
      "campaign_name": "260303 일반 전환 캠페인"
    },
    {
      "spend": 194679.0,
      "impressions": 12904,
      "clicks": 217,
      "reach": 0,
      "ctr": 1.68,
      "cpc": 0.0,
      "cpm": 15087.0,
      "purchases": 2,
      "purchase_value": 69738.0,
      "roas": 0.36,
      "cpa": 97340.0,
      "ad_id": "120243877242080020",
      "ad_name": "260313 KTX 조금덜소프트_27",
      "adset_name": "260313 KTX 전환",
      "campaign_name": "260303 일반 전환 캠페인"
    },
    {
      "spend": 102620.0,
      "impressions": 4701,
      "clicks": 79,
      "reach": 0,
      "ctr": 1.68,
      "cpc": 0.0,
      "cpm": 21829.0,
      "purchases": 1,
      "purchase_value": 36605.0,
      "roas": 0.36,
      "cpa": 102620.0,
      "ad_id": "120243954846900020",
      "ad_name": "260315 KTX 조금덜소프트_27",
      "adset_name": "260315 KTX 댓글유도",
      "campaign_name": "260303 일반 전환 캠페인"
    },
    {
      "spend": 79076.0,
      "impressions": 1831,
      "clicks": 64,
      "reach": 0,
      "ctr": 3.5,
      "cpc": 0.0,
      "cpm": 43187.0,
      "purchases": 1,
      "purchase_value": 129600.0,
      "roas": 1.64,
      "cpa": 79076.0,
      "ad_id": "120243954678250020",
      "ad_name": "260313 KTX 소프트 ASMR_27",
      "adset_name": "260315 KTX - 메신저 전환",
      "campaign_name": "전환 메신저 [전환수 목표]"
    },
    {
      "spend": 65605.0,
      "impressions": 1090,
      "clicks": 25,
      "reach": 0,
      "ctr": 2.29,
      "cpc": 0.0,
      "cpm": 60188.0,
      "purchases": 1,
      "purchase_value": 99600.0,
      "roas": 1.52,
      "cpa": 65605.0,
      "ad_id": "120242792148010020",
      "ad_name": "ASC_제미나이3",
      "adset_name": "260216_ASC_1차광고_세트",
      "campaign_name": "260216_ASC_1차광고"
    },
    {
      "spend": 52598.0,
      "impressions": 2983,
      "clicks": 48,
      "reach": 0,
      "ctr": 1.61,
      "cpc": 0.0,
      "cpm": 17633.0,
      "purchases": 3,
      "purchase_value": 106342.0,
      "roas": 2.02,
      "cpa": 17533.0,
      "ad_id": "120243954846910020",
      "ad_name": "260315 KTX 조금덜소프트 카카오_27 - 사본",
      "adset_name": "260315 KTX 댓글유도",
      "campaign_name": "260303 일반 전환 캠페인"
    },
    {
      "spend": 47450.0,
      "impressions": 771,
      "clicks": 27,
      "reach": 0,
      "ctr": 3.5,
      "cpc": 0.0,
      "cpm": 61543.0,
      "purchases": 2,
      "purchase_value": 165168.0,
      "roas": 3.48,
      "cpa": 23725.0,
      "ad_id": "120243403696300020",
      "ad_name": "260303 장윤주 브랜디드 슈링크",
      "adset_name": "260303 브랜디드 슈링크",
      "campaign_name": "260303 일반 전환 캠페인"
    },
    {
      "spend": 38341.0,
      "impressions": 1693,
      "clicks": 13,
      "reach": 0,
      "ctr": 0.77,
      "cpc": 0.0,
      "cpm": 22647.0,
      "purchases": 0,
      "purchase_value": 0.0,
      "roas": 0.0,
      "cpa": 0.0,
      "ad_id": "120244001333230020",
      "ad_name": "KTX_소프트1_자막 - 사본",
      "adset_name": "260216_ASC_1차광고_세트",
      "campaign_name": "260216_ASC_1차광고"
    },
    {
      "spend": 18066.0,
      "impressions": 301,
      "clicks": 10,
      "reach": 0,
      "ctr": 3.32,
      "cpc": 0.0,
      "cpm": 60020.0,
      "purchases": 0,
      "purchase_value": 0.0,
      "roas": 0.0,
      "cpa": 0.0,
      "ad_id": "120243967839280020",
      "ad_name": "260313_백지연_이뻐지는습관",
      "adset_name": "260315_백지연_1차",
      "campaign_name": "260303 일반 전환 캠페인"
    },
    {
      "spend": 15663.0,
      "impressions": 520,
      "clicks": 37,
      "reach": 0,
      "ctr": 7.12,
      "cpc": 0.0,
      "cpm": 30121.0,
      "purchases": 0,
      "purchase_value": 0.0,
      "roas": 0.0,
      "cpa": 0.0,
      "ad_id": "120243954941020020",
      "ad_name": "260315 KTX1메신저",
      "adset_name": "260315 KTX 메신저",
      "campaign_name": "전환 메신저 [대화수 목표]"
    }
  ]
}