{
  "last_updated": "2026-03-23T06:20:16.159653+09:00",
  "campaigns": [
    {
      "spend": 10045389.0,
      "impressions": 361629,
      "clicks": 7584,
      "reach": 283560,
      "ctr": 2.1,
      "cpc": 1325.0,
      "cpm": 27778.0,
      "purchases": 203,
      "purchase_value": 13925581.0,
      "roas": 1.39,
      "cpa": 49485.0,
      "campaign_id": "120243403518660020",
      "campaign_name": "260303 일반 전환 캠페인"
    },
    {
      "spend": 6062030.0,
      "impressions": 87012,
      "clicks": 2385,
      "reach": 48660,
      "ctr": 2.74,
      "cpc": 2542.0,
      "cpm": 69669.0,
      "purchases": 134,
      "purchase_value": 10714900.0,
      "roas": 1.77,
      "cpa": 45239.0,
      "campaign_id": "120242695180060020",
      "campaign_name": "260216_ASC_1차광고"
    },
    {
      "spend": 1076186.0,
      "impressions": 31317,
      "clicks": 2034,
      "reach": 13418,
      "ctr": 6.49,
      "cpc": 529.0,
      "cpm": 34364.0,
      "purchases": 1,
      "purchase_value": 64300.0,
      "roas": 0.06,
      "cpa": 1076186.0,
      "campaign_id": "120242416319530020",
      "campaign_name": "전환 메신저 [대화수 목표]"
    },
    {
      "spend": 410990.0,
      "impressions": 8787,
      "clicks": 323,
      "reach": 7144,
      "ctr": 3.68,
      "cpc": 1272.0,
      "cpm": 46773.0,
      "purchases": 8,
      "purchase_value": 510500.0,
      "roas": 1.24,
      "cpa": 51374.0,
      "campaign_id": "120243954678190020",
      "campaign_name": "전환 메신저 [전환수 목표]"
    }
  ],
  "data": [
    {
      "spend": 10045389.0,
      "impressions": 361629,
      "clicks": 7584,
      "reach": 283560,
      "ctr": 2.1,
      "cpc": 1325.0,
      "cpm": 27778.0,
      "purchases": 203,
      "purchase_value": 13925581.0,
      "roas": 1.39,
      "cpa": 49485.0,
      "campaign_id": "120243403518660020",
      "campaign_name": "260303 일반 전환 캠페인"
    },
    {
      "spend": 6062030.0,
      "impressions": 87012,
      "clicks": 2385,
      "reach": 48660,
      "ctr": 2.74,
      "cpc": 2542.0,
      "cpm": 69669.0,
      "purchases": 134,
      "purchase_value": 10714900.0,
      "roas": 1.77,
      "cpa": 45239.0,
      "campaign_id": "120242695180060020",
      "campaign_name": "260216_ASC_1차광고"
    },
    {
      "spend": 1076186.0,
      "impressions": 31317,
      "clicks": 2034,
      "reach": 13418,
      "ctr": 6.49,
      "cpc": 529.0,
      "cpm": 34364.0,
      "purchases": 1,
      "purchase_value": 64300.0,
      "roas": 0.06,
      "cpa": 1076186.0,
      "campaign_id": "120242416319530020",
      "campaign_name": "전환 메신저 [대화수 목표]"
    },
    {
      "spend": 410990.0,
      "impressions": 8787,
      "clicks": 323,
      "reach": 7144,
      "ctr": 3.68,
      "cpc": 1272.0,
      "cpm": 46773.0,
      "purchases": 8,
      "purchase_value": 510500.0,
      "roas": 1.24,
      "cpa": 51374.0,
      "campaign_id": "120243954678190020",
      "campaign_name": "전환 메신저 [전환수 목표]"
    }
  ]
}