{
  "last_updated": "2026-03-24T04:00:27.950084+09:00",
  "campaigns": [
    {
      "spend": 10650468.0,
      "impressions": 374203,
      "clicks": 7833,
      "reach": 287921,
      "ctr": 2.09,
      "cpc": 1360.0,
      "cpm": 28462.0,
      "purchases": 209,
      "purchase_value": 14332249.0,
      "roas": 1.35,
      "cpa": 50959.0,
      "campaign_id": "120243403518660020",
      "campaign_name": "260303 일반 전환 캠페인"
    },
    {
      "spend": 6196794.0,
      "impressions": 89855,
      "clicks": 2445,
      "reach": 49959,
      "ctr": 2.72,
      "cpc": 2534.0,
      "cpm": 68964.0,
      "purchases": 139,
      "purchase_value": 11076000.0,
      "roas": 1.79,
      "cpa": 44581.0,
      "campaign_id": "120242695180060020",
      "campaign_name": "260216_ASC_1차광고"
    },
    {
      "spend": 1127554.0,
      "impressions": 32935,
      "clicks": 2152,
      "reach": 13989,
      "ctr": 6.53,
      "cpc": 524.0,
      "cpm": 34236.0,
      "purchases": 1,
      "purchase_value": 64300.0,
      "roas": 0.06,
      "cpa": 1127554.0,
      "campaign_id": "120242416319530020",
      "campaign_name": "전환 메신저 [대화수 목표]"
    },
    {
      "spend": 464618.0,
      "impressions": 9810,
      "clicks": 359,
      "reach": 7935,
      "ctr": 3.66,
      "cpc": 1294.0,
      "cpm": 47362.0,
      "purchases": 11,
      "purchase_value": 702900.0,
      "roas": 1.51,
      "cpa": 42238.0,
      "campaign_id": "120243954678190020",
      "campaign_name": "전환 메신저 [전환수 목표]"
    }
  ],
  "data": [
    {
      "spend": 10650468.0,
      "impressions": 374203,
      "clicks": 7833,
      "reach": 287921,
      "ctr": 2.09,
      "cpc": 1360.0,
      "cpm": 28462.0,
      "purchases": 209,
      "purchase_value": 14332249.0,
      "roas": 1.35,
      "cpa": 50959.0,
      "campaign_id": "120243403518660020",
      "campaign_name": "260303 일반 전환 캠페인"
    },
    {
      "spend": 6196794.0,
      "impressions": 89855,
      "clicks": 2445,
      "reach": 49959,
      "ctr": 2.72,
      "cpc": 2534.0,
      "cpm": 68964.0,
      "purchases": 139,
      "purchase_value": 11076000.0,
      "roas": 1.79,
      "cpa": 44581.0,
      "campaign_id": "120242695180060020",
      "campaign_name": "260216_ASC_1차광고"
    },
    {
      "spend": 1127554.0,
      "impressions": 32935,
      "clicks": 2152,
      "reach": 13989,
      "ctr": 6.53,
      "cpc": 524.0,
      "cpm": 34236.0,
      "purchases": 1,
      "purchase_value": 64300.0,
      "roas": 0.06,
      "cpa": 1127554.0,
      "campaign_id": "120242416319530020",
      "campaign_name": "전환 메신저 [대화수 목표]"
    },
    {
      "spend": 464618.0,
      "impressions": 9810,
      "clicks": 359,
      "reach": 7935,
      "ctr": 3.66,
      "cpc": 1294.0,
      "cpm": 47362.0,
      "purchases": 11,
      "purchase_value": 702900.0,
      "roas": 1.51,
      "cpa": 42238.0,
      "campaign_id": "120243954678190020",
      "campaign_name": "전환 메신저 [전환수 목표]"
    }
  ]
}