{
  "last_updated": "2026-03-18T08:26:12.813613+09:00",
  "campaigns": [
    {
      "spend": 5491250.0,
      "impressions": 232781,
      "clicks": 4635,
      "reach": 193043,
      "ctr": 1.99,
      "cpc": 1185.0,
      "cpm": 23590.0,
      "purchases": 113,
      "purchase_value": 7762032.0,
      "roas": 1.41,
      "cpa": 48595.0,
      "campaign_id": "120243403518660020",
      "campaign_name": "260303 일반 전환 캠페인"
    },
    {
      "spend": 5309694.0,
      "impressions": 73634,
      "clicks": 2036,
      "reach": 40444,
      "ctr": 2.77,
      "cpc": 2608.0,
      "cpm": 72109.0,
      "purchases": 112,
      "purchase_value": 9150200.0,
      "roas": 1.72,
      "cpa": 47408.0,
      "campaign_id": "120242695180060020",
      "campaign_name": "260216_ASC_1차광고"
    },
    {
      "spend": 841695.0,
      "impressions": 24277,
      "clicks": 1516,
      "reach": 10424,
      "ctr": 6.24,
      "cpc": 555.0,
      "cpm": 34670.0,
      "purchases": 1,
      "purchase_value": 64300.0,
      "roas": 0.08,
      "cpa": 841695.0,
      "campaign_id": "120242416319530020",
      "campaign_name": "전환 메신저 [대화수 목표]"
    },
    {
      "spend": 224414.0,
      "impressions": 4664,
      "clicks": 186,
      "reach": 4101,
      "ctr": 3.99,
      "cpc": 1207.0,
      "cpm": 48116.0,
      "purchases": 3,
      "purchase_value": 223500.0,
      "roas": 1.0,
      "cpa": 74805.0,
      "campaign_id": "120243954678190020",
      "campaign_name": "전환 메신저 [전환수 목표]"
    }
  ],
  "data": [
    {
      "spend": 5491250.0,
      "impressions": 232781,
      "clicks": 4635,
      "reach": 193043,
      "ctr": 1.99,
      "cpc": 1185.0,
      "cpm": 23590.0,
      "purchases": 113,
      "purchase_value": 7762032.0,
      "roas": 1.41,
      "cpa": 48595.0,
      "campaign_id": "120243403518660020",
      "campaign_name": "260303 일반 전환 캠페인"
    },
    {
      "spend": 5309694.0,
      "impressions": 73634,
      "clicks": 2036,
      "reach": 40444,
      "ctr": 2.77,
      "cpc": 2608.0,
      "cpm": 72109.0,
      "purchases": 112,
      "purchase_value": 9150200.0,
      "roas": 1.72,
      "cpa": 47408.0,
      "campaign_id": "120242695180060020",
      "campaign_name": "260216_ASC_1차광고"
    },
    {
      "spend": 841695.0,
      "impressions": 24277,
      "clicks": 1516,
      "reach": 10424,
      "ctr": 6.24,
      "cpc": 555.0,
      "cpm": 34670.0,
      "purchases": 1,
      "purchase_value": 64300.0,
      "roas": 0.08,
      "cpa": 841695.0,
      "campaign_id": "120242416319530020",
      "campaign_name": "전환 메신저 [대화수 목표]"
    },
    {
      "spend": 224414.0,
      "impressions": 4664,
      "clicks": 186,
      "reach": 4101,
      "ctr": 3.99,
      "cpc": 1207.0,
      "cpm": 48116.0,
      "purchases": 3,
      "purchase_value": 223500.0,
      "roas": 1.0,
      "cpa": 74805.0,
      "campaign_id": "120243954678190020",
      "campaign_name": "전환 메신저 [전환수 목표]"
    }
  ]
}