{
  "last_updated": "2026-03-21T23:21:04.345096+09:00",
  "last_updated_kst": "2026-03-21 23:21 KST",
  "monthly": {
    "spend": 16971861.0,
    "impressions": 462234,
    "clicks": 11606,
    "reach": 309000,
    "ctr": 2.51,
    "cpc": 1462.0,
    "cpm": 36717.0,
    "purchases": 310,
    "purchase_value": 22949403.0,
    "roas": 1.35,
    "cpa": 54748.0
  },
  "month": {
    "spend": 16971861.0,
    "impressions": 462234,
    "clicks": 11606,
    "reach": 309000,
    "ctr": 2.51,
    "cpc": 1462.0,
    "cpm": 36717.0,
    "purchases": 310,
    "purchase_value": 22949403.0,
    "roas": 1.35,
    "cpa": 54748.0
  },
  "today": {
    "spend": 998283.0,
    "impressions": 21632,
    "clicks": 617,
    "reach": 18010,
    "ctr": 2.85,
    "cpc": 1618.0,
    "cpm": 46148.0,
    "purchases": 18,
    "purchase_value": 1519799.0,
    "roas": 1.52,
    "cpa": 55460.0
  },
  "yesterday": {
    "spend": 1016976.0,
    "impressions": 24226,
    "clicks": 631,
    "reach": 21225,
    "ctr": 2.6,
    "cpc": 1612.0,
    "cpm": 41979.0,
    "purchases": 17,
    "purchase_value": 1359302.0,
    "roas": 1.34,
    "cpa": 59822.0
  },
  "last_7d": {
    "spend": 9318412.0,
    "impressions": 346388,
    "clicks": 7821,
    "reach": 268633,
    "ctr": 2.26,
    "cpc": 1191.0,
    "cpm": 26902.0,
    "purchases": 171,
    "purchase_value": 11490952.0,
    "roas": 1.23,
    "cpa": 54494.0
  },
  "campaigns": [
    {
      "spend": 8913090.0,
      "impressions": 334366,
      "clicks": 6946,
      "reach": 267032,
      "ctr": 2.08,
      "cpc": 1283.0,
      "cpm": 26657.0,
      "purchases": 166,
      "purchase_value": 11327781.0,
      "roas": 1.27,
      "cpa": 53693.0,
      "campaign_id": "120243403518660020",
      "campaign_name": "260303 일반 전환 캠페인"
    },
    {
      "spend": 5828814.0,
      "impressions": 82863,
      "clicks": 2272,
      "reach": 45874,
      "ctr": 2.74,
      "cpc": 2565.0,
      "cpm": 70343.0,
      "purchases": 125,
      "purchase_value": 10119400.0,
      "roas": 1.74,
      "cpa": 46631.0,
      "campaign_id": "120242695180060020",
      "campaign_name": "260216_ASC_1차광고"
    },
    {
      "spend": 1011005.0,
      "impressions": 29215,
      "clicks": 1880,
      "reach": 12512,
      "ctr": 6.44,
      "cpc": 538.0,
      "cpm": 34606.0,
      "purchases": 1,
      "purchase_value": 64300.0,
      "roas": 0.06,
      "cpa": 1011005.0,
      "campaign_id": "120242416319530020",
      "campaign_name": "전환 메신저 [대화수 목표]"
    },
    {
      "spend": 342806.0,
      "impressions": 7279,
      "clicks": 276,
      "reach": 6009,
      "ctr": 3.79,
      "cpc": 1242.0,
      "cpm": 47095.0,
      "purchases": 7,
      "purchase_value": 473400.0,
      "roas": 1.38,
      "cpa": 48972.0,
      "campaign_id": "120243954678190020",
      "campaign_name": "전환 메신저 [전환수 목표]"
    }
  ],
  "goals": {
    "roas": 2.5,
    "spend": 3000000,
    "revenue": 7500000,
    "budget": 3000000
  }
}